{
  "bloc": 10,
  "summary": "Problématique : Utilisation de la visioconférence dans l'enseignement scolaire pour améliorer les apprentissages des élèves.\n\nMéthode : Adoption de modalités de travail en groupe, préparation et exploitation de la séance de visioconférence, animation des débats par l'enseignant, formation de tous les enseignants intéressés à la manipulation du dispositif et aux méthodes de pédagogie de communication.\n\nRésultats : Les élèves doivent sentir qu'ils sont impliqués dans une situation réelle de communication pour être motivés, l'enseignant reste le garant essentiel des apprentissages et doit adapter ses interventions selon le déroulement constaté, les compétences de communication des élèves doivent être développées, le contenu des interventions et des débats doit correspondre au niveau attendu par tout enseignant.\n\nValorisation : Études exploratoires envisageant la visioconférence sous un angle général, nécessitant une formation de tous les enseignants intéressés.",
  "source_pdf": "https://edutice.hal.science/edutice-00000413v1/document",
  "score": 0.7082,
  "translated": false
}